{
    "version": "https://jsonfeed.org/version/1",
    "title": "sunsaisai",
    "subtitle": "",
    "icon": "http://example.com/images/favicon.ico",
    "description": "",
    "home_page_url": "http://example.com",
    "items": [
        {
            "id": "http://example.com/2023/08/16/hello-world/",
            "url": "http://example.com/2023/08/16/hello-world/",
            "title": "孙赛赛测试",
            "date_published": "2023-08-16T02:47:48.563Z",
            "content_html": "<h2 id=\"孙赛赛测试\"><a class=\"anchor\" href=\"#孙赛赛测试\">#</a> 孙赛赛测试</h2>\n<h3 id=\"777777777777777777777\"><a class=\"anchor\" href=\"#777777777777777777777\">#</a> 777777777777777777777</h3>\n",
            "tags": []
        }
    ]
}